chen/__init__.py
chen/_version.py
chen/juliapkg.json
chen/torch.py
chen_signatures-0.4.0.dist-info/METADATA
chen_signatures-0.4.0.dist-info/WHEEL
chen_signatures-0.4.0.dist-info/top_level.txt
chen_signatures-0.4.0.dist-info/RECORD
