Metadata-Version: 2.4
Name: chen-signatures
Version: 0.4.0
Summary: Fast path signatures
Author-email: Alessandro Combi <alecombi94@gmail.com>
License-Expression: MIT
Project-URL: Homepage, https://github.com/aleCombi/ChenSignatures.jl
Project-URL: Repository, https://github.com/aleCombi/ChenSignatures.jl
Project-URL: Issues, https://github.com/aleCombi/ChenSignatures.jl/issues
Keywords: signatures,rough-paths,time-series,machine-learning
Classifier: Development Status :: 4 - Beta
Classifier: Intended Audience :: Science/Research
Classifier: Programming Language :: Python :: 3
Classifier: Programming Language :: Python :: 3.9
Classifier: Programming Language :: Python :: 3.10
Classifier: Programming Language :: Python :: 3.11
Classifier: Programming Language :: Python :: 3.12
Classifier: Programming Language :: Python :: 3.13
Classifier: Topic :: Scientific/Engineering :: Mathematics
Requires-Python: >=3.9
Requires-Dist: juliapkg>=0.1.10
Requires-Dist: juliacall>=0.9.20
Requires-Dist: numpy>=1.20.0
Provides-Extra: dev
Requires-Dist: pytest>=7.0.0; extra == "dev"
Requires-Dist: pytest-cov>=4.0.0; extra == "dev"
Provides-Extra: torch
Requires-Dist: torch>=2.0.0; extra == "torch"
Provides-Extra: benchmark
Requires-Dist: pysiglib>=0.2.2; extra == "benchmark"
Provides-Extra: all
Requires-Dist: pytest>=7.0.0; extra == "all"
Requires-Dist: pytest-cov>=4.0.0; extra == "all"
Requires-Dist: torch>=2.0.0; extra == "all"
Requires-Dist: pysiglib>=0.2.2; extra == "all"
